web_mini/__init__.py
web_mini/clrs.py
web_mini/const.py
web_mini/css.py
web_mini/html.py
web_mini/py.typed
web_mini/recache.py
web_mini-1.4.1.dist-info/LICENSE
web_mini-1.4.1.dist-info/METADATA
web_mini-1.4.1.dist-info/WHEEL
web_mini-1.4.1.dist-info/top_level.txt
web_mini-1.4.1.dist-info/zip-safe
web_mini-1.4.1.dist-info/RECORD
