Metadata-Version: 2.1
Name: web-mini
Version: 1.4.1
Summary: web-mini -- efficient css and html minifer inspired by css-html-js-minify
Home-page: https://ari.lt/gh/web-mini
Author: Ari Archer
Author-email: ari@ari.lt
License: GPLv3+
Keywords: css,html,web,www,https. minifier,css minifier,html minifier,typed,html5,min
Classifier: Development Status :: 5 - Production/Stable
Classifier: Intended Audience :: Developers
Classifier: License :: OSI Approved :: GNU General Public License v3 or later (GPLv3+)
Classifier: Operating System :: OS Independent
Classifier: Programming Language :: Python :: 3
Classifier: Programming Language :: Python :: 3.8
Classifier: Programming Language :: Python :: 3.9
Classifier: Programming Language :: Python :: 3.10
Classifier: Programming Language :: Python :: 3.11
Classifier: Programming Language :: Python :: 3.12
Classifier: Topic :: Internet :: WWW/HTTP
Classifier: Topic :: Software Development :: Libraries :: Python Modules
Classifier: Typing :: Typed
License-File: LICENSE
